counter_johnson.v

/* 
 * Counter (Johnson code) Verilog example (iverilog 10.1)
 *
 */
 
 module counter
 (
     input clock,
     input reset,
     input up_down,
     output [3:0] out
 );

    reg [3:0] out_tmp;

    always @ (posedge(clock), reset)
    begin
        if (reset == 1'b1)
            out_tmp = 0;
        else if (up_down == 1'b1)
            out_tmp = {out_tmp[2:0], ~out_tmp[3]};
        else
            out_tmp = {~out_tmp[0], out_tmp[3:1]};
    end

    assign out = out_tmp;

endmodule

counter_johnson_tb.v

/* 
 * Counter (Johnson code) Verilog example tesbench (iverilog 10.1)
 *
 */

`timescale 1ns/1ps

`include "counter_johnson.v"
 
 module counter_johnson_tb;

    /* inputs */
    reg Clock;
    reg Up_down;
    reg Reset;

    /* outputs */
    wire [3:0] Out;

    /* variables */
    integer i;

    /* instantiate the uut */
    counter uut(.clock(Clock), .reset(Reset), .up_down(Up_down), .out(Out));

    initial
    begin
        $display("Up/down Johnson's counter testbench...\n");
        $dumpfile("counter_1_test.vcd");
        $dumpvars;

        Clock = 1'b0;
        i = 0;
        Up_down = 0;
        Reset = 0;
        #10;
        Reset = 1;
        #5;
        Reset = 0;
        #20;

        while (i < 64) begin
            if (i == 32) begin
                Up_down = 1;
                $display("Up/Down change");
                end
            #10;
            Clock = ~Clock;
            i = i + 1;
            $display("Counter out: %b\ttime = %d", Out, $time);
        end

        $display("Done...");
    end

endmodule

counter_1_test.vcd
$date
	Wed Nov 21 00:08:39 2018
$end
$version
	Icarus Verilog
$end
$timescale
	1ps
$end
$scope module counter_johnson_tb $end
$var wire 4 ! Out [3:0] $end
$var reg 1 " Clock $end
$var reg 1 # Reset $end
$var reg 1 $ Up_down $end
$var integer 32 % i [31:0] $end
$scope module uut $end
$var wire 1 " clock $end
$var wire 4 & out [3:0] $end
$var wire 1 # reset $end
$var wire 1 $ up_down $end
$var reg 4 ' out_tmp [3:0] $end
$upscope $end
$upscope $end
$enddefinitions $end
#0
$dumpvars
bx '
bx &
b0 %
0$
0#
0"
bx !
$end
#10000
b0 !
b0 &
b0 '
1#
#15000
b1000 !
b1000 &
b1000 '
0#
#45000
b1100 !
b1100 &
b1100 '
b1 %
1"
#55000
b10 %
0"
#65000
b1110 !
b1110 &
b1110 '
b11 %
1"
#75000
b100 %
0"
#85000
b1111 !
b1111 &
b1111 '
b101 %
1"
#95000
b110 %
0"
#105000
b111 !
b111 &
b111 '
b111 %
1"
#115000
b1000 %
0"
#125000
b11 !
b11 &
b11 '
b1001 %
1"
#135000
b1010 %
0"
#145000
b1 !
b1 &
b1 '
b1011 %
1"
#155000
b1100 %
0"
#165000
b0 !
b0 &
b0 '
b1101 %
1"
#175000
b1110 %
0"
#185000
b1000 !
b1000 &
b1000 '
b1111 %
1"
#195000
b10000 %
0"
#205000
b1100 !
b1100 &
b1100 '
b10001 %
1"
#215000
b10010 %
0"
#225000
b1110 !
b1110 &
b1110 '
b10011 %
1"
#235000
b10100 %
0"
#245000
b1111 !
b1111 &
b1111 '
b10101 %
1"
#255000
b10110 %
0"
#265000
b111 !
b111 &
b111 '
b10111 %
1"
#275000
b11000 %
0"
#285000
b11 !
b11 &
b11 '
b11001 %
1"
#295000
b11010 %
0"
#305000
b1 !
b1 &
b1 '
b11011 %
1"
#315000
b11100 %
0"
#325000
b0 !
b0 &
b0 '
b11101 %
1"
#335000
b11110 %
0"
#345000
b1000 !
b1000 &
b1000 '
b11111 %
1"
#355000
1$
b100000 %
0"
#365000
b0 !
b0 &
b0 '
b100001 %
1"
#375000
b100010 %
0"
#385000
b1 !
b1 &
b1 '
b100011 %
1"
#395000
b100100 %
0"
#405000
b11 !
b11 &
b11 '
b100101 %
1"
#415000
b100110 %
0"
#425000
b111 !
b111 &
b111 '
b100111 %
1"
#435000
b101000 %
0"
#445000
b1111 !
b1111 &
b1111 '
b101001 %
1"
#455000
b101010 %
0"
#465000
b1110 !
b1110 &
b1110 '
b101011 %
1"
#475000
b101100 %
0"
#485000
b1100 !
b1100 &
b1100 '
b101101 %
1"
#495000
b101110 %
0"
#505000
b1000 !
b1000 &
b1000 '
b101111 %
1"
#515000
b110000 %
0"
#525000
b0 !
b0 &
b0 '
b110001 %
1"
#535000
b110010 %
0"
#545000
b1 !
b1 &
b1 '
b110011 %
1"
#555000
b110100 %
0"
#565000
b11 !
b11 &
b11 '
b110101 %
1"
#575000
b110110 %
0"
#585000
b111 !
b111 &
b111 '
b110111 %
1"
#595000
b111000 %
0"
#605000
b1111 !
b1111 &
b1111 '
b111001 %
1"
#615000
b111010 %
0"
#625000
b1110 !
b1110 &
b1110 '
b111011 %
1"
#635000
b111100 %
0"
#645000
b1100 !
b1100 &
b1100 '
b111101 %
1"
#655000
b111110 %
0"
#665000
b1000 !
b1000 &
b1000 '
b111111 %
1"
#675000
b1000000 %
0"
